uvrev/__init__.py
uvrev/cli.py
uvrev/commands.py
uvrev/constants.py
uvrev/differ.py
uvrev/exceptions.py
uvrev/io.py
uvrev/operations.py
uvrev/parser.py
uvrev/terminal.py
uvrev/types.py
uvrev-0.1.4.dist-info/METADATA
uvrev-0.1.4.dist-info/WHEEL
uvrev-0.1.4.dist-info/entry_points.txt
uvrev-0.1.4.dist-info/licenses/LICENSE
uvrev-0.1.4.dist-info/RECORD
