Metadata-Version: 2.4
Name: uvrev
Version: 0.1.4
Summary: uv env manager to enable conda-style revision tracking
Project-URL: Homepage, https://gitlab.com/Kound/uvrev
Project-URL: Documentation, https://gitlab.com/Kound/uvrev/-/blob/main/README.md
Project-URL: Changelog, https://gitlab.com/Kound/uvrev/-/tags
Project-URL: Issues, https://gitlab.com/Kound/uvrev/-/issues
Project-URL: Source Code, https://gitlab.com/Kound/uvrev
Author-email: Carli* Freudenberg <kound@posteo.de>
License-Expression: MIT
License-File: LICENSE
Classifier: Development Status :: 4 - Beta
Classifier: Environment :: Console
Classifier: Intended Audience :: Developers
Classifier: License :: OSI Approved :: MIT License
Classifier: Natural Language :: English
Classifier: Operating System :: OS Independent
Classifier: Programming Language :: Python
Classifier: Programming Language :: Python :: 3.10
Classifier: Programming Language :: Python :: 3.11
Classifier: Programming Language :: Python :: 3.12
Classifier: Programming Language :: Python :: 3.13
Classifier: Programming Language :: Python :: 3.14
Classifier: Programming Language :: Python :: Implementation :: CPython
Classifier: Programming Language :: Python :: Implementation :: PyPy
Classifier: Topic :: Software Development :: Libraries :: Python Modules
Classifier: Typing :: Typed
Requires-Python: >=3.12
Requires-Dist: click>=8
Requires-Dist: packaging>=25.0
Requires-Dist: platformdirs>=4
Requires-Dist: tomlkit>=0.13
